odoo/addons/web_widget_x2many_2d_matrix_example/README.rst
odoo/addons/web_widget_x2many_2d_matrix_example/__init__.py
odoo/addons/web_widget_x2many_2d_matrix_example/__manifest__.py
odoo/addons/web_widget_x2many_2d_matrix_example/demo/x2m.demo.csv
odoo/addons/web_widget_x2many_2d_matrix_example/i18n/ca.po
odoo/addons/web_widget_x2many_2d_matrix_example/i18n/es.po
odoo/addons/web_widget_x2many_2d_matrix_example/i18n/pt_BR.po
odoo/addons/web_widget_x2many_2d_matrix_example/i18n/web_widget_x2many_2d_matrix_example.pot
odoo/addons/web_widget_x2many_2d_matrix_example/i18n/zh_CN.po
odoo/addons/web_widget_x2many_2d_matrix_example/models/__init__.py
odoo/addons/web_widget_x2many_2d_matrix_example/models/res_users.py
odoo/addons/web_widget_x2many_2d_matrix_example/models/x2m_demo.py
odoo/addons/web_widget_x2many_2d_matrix_example/readme/CONTRIBUTORS.rst
odoo/addons/web_widget_x2many_2d_matrix_example/readme/DESCRIPTION.rst
odoo/addons/web_widget_x2many_2d_matrix_example/security/ir.model.access.csv
odoo/addons/web_widget_x2many_2d_matrix_example/static/description/icon.png
odoo/addons/web_widget_x2many_2d_matrix_example/static/description/index.html
odoo/addons/web_widget_x2many_2d_matrix_example/views/x2m_demo.xml
odoo/addons/web_widget_x2many_2d_matrix_example/wizard/__init__.py
odoo/addons/web_widget_x2many_2d_matrix_example/wizard/x2m_matrix.py
odoo/addons/web_widget_x2many_2d_matrix_example/wizard/x2m_matrix.xml
odoo12_addon_web_widget_x2many_2d_matrix_example-12.0.1.1.1.dist-info/METADATA
odoo12_addon_web_widget_x2many_2d_matrix_example-12.0.1.1.1.dist-info/WHEEL
odoo12_addon_web_widget_x2many_2d_matrix_example-12.0.1.1.1.dist-info/top_level.txt
odoo12_addon_web_widget_x2many_2d_matrix_example-12.0.1.1.1.dist-info/RECORD
