Metadata-Version: 2.1
Name: odoo12-addon-web-widget-x2many-2d-matrix-example
Version: 12.0.1.1.1
Summary: A small example on how to use `web_widget_x2many_2d_matrix`.
Home-page: https://github.com/OCA/web
Author: Camptocamp, Odoo Community Association (OCA)
Author-email: support@odoo-community.org
License: AGPL-3
Platform: UNKNOWN
Classifier: Programming Language :: Python
Classifier: Framework :: Odoo
Classifier: Framework :: Odoo :: 12.0
Classifier: License :: OSI Approved :: GNU Affero General Public License v3
Requires-Python: >=3.5
Requires-Dist: odoo12-addon-web-widget-x2many-2d-matrix
Requires-Dist: odoo (<12.1dev,>=12.0a)
